README.rst
setup.cfg
setup.py
./__init__.py
./product.py
./product.xml
./tryton.cfg
./locale/de_DE.po
./tests/__init__.py
./tests/test_product.py
./tests/test_views_depends.py
./view/product_form.xml
./view/template_form.xml
./view/variation_attributes_form.xml
./view/variation_attributes_tree.xml
openlabs_nereid_catalog_variants.egg-info/PKG-INFO
openlabs_nereid_catalog_variants.egg-info/SOURCES.txt
openlabs_nereid_catalog_variants.egg-info/dependency_links.txt
openlabs_nereid_catalog_variants.egg-info/entry_points.txt
openlabs_nereid_catalog_variants.egg-info/not-zip-safe
openlabs_nereid_catalog_variants.egg-info/requires.txt
openlabs_nereid_catalog_variants.egg-info/top_level.txt